qianqiucloudsdk/__init__.py
qianqiucloudsdk/db.py
qianqiucloudsdk/iotdb.py
qianqiucloudsdk-0.0.9.data/scripts/db.py
qianqiucloudsdk-0.0.9.data/scripts/iotdb.py
qianqiucloudsdk-0.0.9.dist-info/METADATA
qianqiucloudsdk-0.0.9.dist-info/WHEEL
qianqiucloudsdk-0.0.9.dist-info/top_level.txt
qianqiucloudsdk-0.0.9.dist-info/RECORD
